landsatmtlparser.py
setup.py
landsatmtlparser.egg-info/PKG-INFO
landsatmtlparser.egg-info/SOURCES.txt
landsatmtlparser.egg-info/dependency_links.txt
landsatmtlparser.egg-info/top_level.txt