Metadata-Version: 1.0
Name: landsatmtlparser
Version: 0.1
Summary: Python package for parsing Landsat metadata files.
Home-page: https://github.com/kbasten/landsatmtlparser
Author: Koen Basten
Author-email: info@kbasten.com
License: MIT
Platform: UNKNOWN
